orchepy_client/__init__.py
orchepy_client/client.py
orchepy_client/exceptions.py
orchepy_client/models.py
orchepy_client/py.typed
orchepy_client-0.1.0.dist-info/METADATA
orchepy_client-0.1.0.dist-info/WHEEL
orchepy_client-0.1.0.dist-info/licenses/LICENSE
orchepy_client-0.1.0.dist-info/RECORD
