Metadata-Version: 2.4
Name: orchepy-client
Version: 0.1.0
Summary: Python client for Orchepy - A lightweight, domain-agnostic event orchestrator
Project-URL: Homepage, https://github.com/derivia/orchepy-python
Project-URL: Repository, https://github.com/derivia/orchepy-python
Project-URL: Documentation, https://github.com/derivia/orchepy-python#readme
Project-URL: Bug Tracker, https://github.com/derivia/orchepy-python/issues
Author-email: Lorran Soares <contato.lorransoares@gmail.com>
License: MIT
License-File: LICENSE
Keywords: automation,kanban,orchepy,orchestration,workflow
Classifier: Development Status :: 3 - Alpha
Classifier: Intended Audience :: Developers
Classifier: License :: OSI Approved :: MIT License
Classifier: Programming Language :: Python :: 3
Classifier: Programming Language :: Python :: 3.11
Classifier: Programming Language :: Python :: 3.12
Classifier: Topic :: Office/Business :: Groupware
Classifier: Topic :: Software Development :: Libraries :: Python Modules
Requires-Python: >=3.11
Requires-Dist: httpx>=0.27.0
Requires-Dist: pydantic>=2.0.0
Provides-Extra: dev
Requires-Dist: mypy>=1.8.0; extra == 'dev'
Requires-Dist: pytest-asyncio>=0.23.0; extra == 'dev'
Requires-Dist: pytest-cov>=5.0.0; extra == 'dev'
Requires-Dist: pytest>=8.0.0; extra == 'dev'
Requires-Dist: ruff>=0.3.0; extra == 'dev'
